removedup.pypy310-pp73-win_amd64.pyd
removedup-1.0.6.dist-info/LICENSE
removedup-1.0.6.dist-info/METADATA
removedup-1.0.6.dist-info/WHEEL
removedup-1.0.6.dist-info/top_level.txt
removedup-1.0.6.dist-info/RECORD
