Metadata-Version: 2.1
Name: removedup
Version: 1.0.6
Summary: Remove duplicates from parallel corpora
Home-page: https://github.com/LibreTranslate/RemoveDUP
Author: Piero Toffanin
Author-email: pt@masseranolabs.com
Requires-Python: >=3.7
License-File: LICENSE
Provides-Extra: test
Requires-Dist: pytest >=6.0 ; extra == 'test'
